prettyqt/__init__.py
prettyqt/__pyinstaller/__init__.py
prettyqt/__pyinstaller/hook-prettyqt.py
prettyqt/animations/__init__.py
prettyqt/animations/animator.py
prettyqt/animations/cursormoveanimation.py
prettyqt/animations/flasheffect.py
prettyqt/animations/fx.py
prettyqt/animations/slideanimation.py
prettyqt/animations/textanimation.py
prettyqt/animations/zoomanimation.py
prettyqt/bluetooth/__init__.py
prettyqt/bluetooth/bluetoothaddress.py
prettyqt/bluetooth/bluetoothdevicediscoveryagent.py
prettyqt/bluetooth/bluetoothdeviceinfo.py
prettyqt/bluetooth/bluetoothhostinfo.py
prettyqt/bluetooth/bluetoothlocaldevice.py
prettyqt/bluetooth/bluetoothserver.py
prettyqt/bluetooth/bluetoothservicediscoveryagent.py
prettyqt/bluetooth/bluetoothserviceinfo.py
prettyqt/bluetooth/bluetoothsocket.py
prettyqt/bluetooth/bluetoothuuid.py
prettyqt/charts/__init__.py
prettyqt/charts/abstractaxis.py
prettyqt/charts/abstractbarseries.py
prettyqt/charts/abstractseries.py
prettyqt/charts/barcategoryaxis.py
prettyqt/charts/barseries.py
prettyqt/charts/barset.py
prettyqt/charts/boxset.py
prettyqt/charts/candlestickset.py
prettyqt/charts/categoryaxis.py
prettyqt/charts/chart.py
prettyqt/charts/chartview.py
prettyqt/charts/datetimeaxis.py
prettyqt/charts/horizontalbarseries.py
prettyqt/charts/horizontalpercentbarseries.py
prettyqt/charts/horizontalstackedbarseries.py
prettyqt/charts/legend.py
prettyqt/charts/lineseries.py
prettyqt/charts/logvalueaxis.py
prettyqt/charts/percentbarseries.py
prettyqt/charts/pieslice.py
prettyqt/charts/polarchart.py
prettyqt/charts/scatterseries.py
prettyqt/charts/stackedbarseries.py
prettyqt/charts/valueaxis.py
prettyqt/charts/xyseries.py
prettyqt/constants/__init__.py
prettyqt/core/__init__.py
prettyqt/core/_calendar.py
prettyqt/core/_datetime.py
prettyqt/core/_locale.py
prettyqt/core/_resource.py
prettyqt/core/_time.py
prettyqt/core/_uuid.py
prettyqt/core/abstractanimation.py
prettyqt/core/abstracteventdispatcher.py
prettyqt/core/abstractitemmodel.py
prettyqt-1.59.4.dist-info/WHEEL
prettyqt-1.59.4.dist-info/entry_points.txt
prettyqt-1.59.4.dist-info/METADATA
prettyqt-1.59.4.dist-info/RECORD
