Metadata-Version: 2.4
Name: PrettyQt
Version: 1.59.4
Summary: A pythonic layer on top of PyQt6 / PySide6
Keywords: components,framework,gui,pyqt,pyside,qt,widgets
Author: Philipp Temminghoff
Author-email: Philipp Temminghoff <philipptemminghoff@gmail.com>
License-Expression: MIT
Classifier: Development Status :: 5 - Production/Stable
Classifier: Environment :: X11 Applications :: Qt
Classifier: Intended Audience :: Developers
Classifier: Operating System :: OS Independent
Classifier: Programming Language :: Python :: 3
Classifier: Programming Language :: Python :: 3 :: Only
Classifier: Programming Language :: Python :: 3.12
Classifier: Programming Language :: Python :: 3.13
Classifier: Topic :: Desktop Environment
Classifier: Topic :: Software Development :: User Interfaces
Classifier: Topic :: Software Development :: Widget Sets
Requires-Dist: anyenv>=0.4.6
Requires-Dist: bidict
Requires-Dist: comtypes ; sys_platform == 'win32'
Requires-Dist: pygments
Requires-Dist: pywin32 ; sys_platform == 'win32'
Requires-Dist: qstylizer
Requires-Dist: sublime-search>=0.1.2
Requires-Dist: orjson ; extra == 'addons'
Requires-Dist: fsspec ; extra == 'addons'
Requires-Dist: pillow ; extra == 'addons'
Requires-Dist: numpy ; extra == 'addons'
Requires-Dist: qtconsole ; extra == 'addons'
Requires-Dist: ipython ; extra == 'addons'
Requires-Dist: lxml ; extra == 'addons'
Requires-Dist: pyqt6 ; extra == 'pyqt6'
Requires-Dist: pyqt6-charts ; extra == 'pyqt6'
Requires-Dist: pyqt6-webengine ; extra == 'pyqt6'
Requires-Dist: pyqt6-qscintilla ; extra == 'pyqt6'
Requires-Dist: pyside6 ; extra == 'pyside6'
Requires-Dist: pyside6-addons ; extra == 'pyside6'
Requires-Python: >=3.12
Project-URL: Changelog, https://github.com/phil65/prettyqt/blob/main/CHANGELOG.md
Project-URL: Documentation, https://phil65.github.io/PrettyQt/index.html
Project-URL: Source, https://github.com/phil65/prettyqt
Project-URL: Tracker, https://github.com/phil65/prettyqt/issues
Provides-Extra: addons
Provides-Extra: pyqt6
Provides-Extra: pyside6
